ionoscloud_dbaas_mariadb/__init__.py
ionoscloud_dbaas_mariadb/api_client.py
ionoscloud_dbaas_mariadb/api_response.py
ionoscloud_dbaas_mariadb/configuration.py
ionoscloud_dbaas_mariadb/exceptions.py
ionoscloud_dbaas_mariadb/rest.py
ionoscloud_dbaas_mariadb/api/__init__.py
ionoscloud_dbaas_mariadb/api/backups_api.py
ionoscloud_dbaas_mariadb/api/clusters_api.py
ionoscloud_dbaas_mariadb/models/__init__.py
ionoscloud_dbaas_mariadb/models/backup.py
ionoscloud_dbaas_mariadb/models/backup_list.py
ionoscloud_dbaas_mariadb/models/backup_list_all_of.py
ionoscloud_dbaas_mariadb/models/backup_response.py
ionoscloud_dbaas_mariadb/models/base_backup.py
ionoscloud_dbaas_mariadb/models/cluster_list.py
ionoscloud_dbaas_mariadb/models/cluster_list_all_of.py
ionoscloud_dbaas_mariadb/models/cluster_metadata.py
ionoscloud_dbaas_mariadb/models/cluster_properties.py
ionoscloud_dbaas_mariadb/models/cluster_response.py
ionoscloud_dbaas_mariadb/models/clusters_get400_response.py
ionoscloud_dbaas_mariadb/models/clusters_get401_response.py
ionoscloud_dbaas_mariadb/models/clusters_get403_response.py
ionoscloud_dbaas_mariadb/models/clusters_get404_response.py
ionoscloud_dbaas_mariadb/models/clusters_get405_response.py
ionoscloud_dbaas_mariadb/models/clusters_get415_response.py
ionoscloud_dbaas_mariadb/models/clusters_get422_response.py
ionoscloud_dbaas_mariadb/models/clusters_get429_response.py
ionoscloud_dbaas_mariadb/models/clusters_get500_response.py
ionoscloud_dbaas_mariadb/models/clusters_get503_response.py
ionoscloud_dbaas_mariadb/models/connection.py
ionoscloud_dbaas_mariadb/models/create_cluster_properties.py
ionoscloud_dbaas_mariadb/models/create_cluster_request.py
ionoscloud_dbaas_mariadb/models/day_of_the_week.py
ionoscloud_dbaas_mariadb/models/db_user.py
ionoscloud_dbaas_mariadb/models/error_message.py
ionoscloud_dbaas_mariadb/models/maintenance_window.py
ionoscloud_dbaas_mariadb/models/mariadb_version.py
ionoscloud_dbaas_mariadb/models/pagination.py
ionoscloud_dbaas_mariadb-1.0.0.dist-info/LICENSE
ionoscloud_dbaas_mariadb-1.0.0.dist-info/METADATA
ionoscloud_dbaas_mariadb-1.0.0.dist-info/WHEEL
ionoscloud_dbaas_mariadb-1.0.0.dist-info/top_level.txt
ionoscloud_dbaas_mariadb-1.0.0.dist-info/RECORD
